squiid_engine/_data_structs.py
squiid_engine/__init__.py
squiid_engine/libsquiid_engine.so
squiid_engine/_backend.py
squiid_engine-0.4.0.dist-info/WHEEL
squiid_engine-0.4.0.dist-info/METADATA
squiid_engine-0.4.0.dist-info/RECORD
squiid_engine-0.4.0.dist-info/LICENSE
