Metadata-Version: 2.3
Name: squiid-engine
Version: 0.4.0
Summary: Squiid Engine Python bindings
License: GPL-3.0-only
Author: TabulateJarl8
Author-email: tabulatejarl8@gmail.com
Requires-Python: >=3.10,<4.0
Classifier: Development Status :: 4 - Beta
Classifier: Intended Audience :: Developers
Classifier: License :: OSI Approved :: GNU General Public License v3 (GPLv3)
Classifier: Programming Language :: Python :: 3
Classifier: Programming Language :: Python :: 3.10
Classifier: Programming Language :: Python :: 3.11
Classifier: Programming Language :: Python :: 3.12
Classifier: Programming Language :: Python :: 3.13
Classifier: Topic :: Software Development
Classifier: Typing :: Typed
Project-URL: Repository, https://gitlab.com/ImaginaryInfinity/squiid-calculator/squiid-bindings
